bmp180.py
circuitpython_bmp180-0.2.0.dist-info/LICENSE
circuitpython_bmp180-0.2.0.dist-info/METADATA
circuitpython_bmp180-0.2.0.dist-info/WHEEL
circuitpython_bmp180-0.2.0.dist-info/top_level.txt
circuitpython_bmp180-0.2.0.dist-info/RECORD
