Metadata-Version: 2.1
Name: circuitpython-bmp180
Version: 0.2.0
Summary: CircuitPython driver for the bmp180 sensor
Author-email: "Jose D. Montoya" <qmc@mailmeto.mozmail.com>
License: MIT
Project-URL: Homepage, https://github.com/jposada202020/CircuitPython_bmp180
Keywords: adafruit,blinka,circuitpython,micropython,bmp180,barometric,pressure,driver,sensor
Classifier: Intended Audience :: Developers
Classifier: Topic :: Software Development :: Libraries
Classifier: Topic :: Software Development :: Embedded Systems
Classifier: Topic :: System :: Hardware
Classifier: License :: OSI Approved :: MIT License
Classifier: Programming Language :: Python :: 3
Provides-Extra: optional
License-File: LICENSE
